CHANGES.txt
LICENSE.txt
MANIFEST.in
README.rst
setup.py
CorpConv.egg-info/PKG-INFO
CorpConv.egg-info/SOURCES.txt
CorpConv.egg-info/dependency_links.txt
CorpConv.egg-info/entry_points.txt
CorpConv.egg-info/top_level.txt
corpconv/__init__.py
corpconv/cli.py
corpconv/corpus_converter.py
corpconv/corpus_readers.py
corpconv/corpus_writers.py