Metadata-Version: 1.1
Name: CorpConv
Version: 0.1.1
Summary: A converter between various corpus formats.
Home-page: https://github.com/tsproisl/CorpConv
Author: Thomas Proisl
Author-email: thomas.proisl@fau.de
License: GNU General Public License v3 or later (GPLv3+)
Download-URL: https://github.com/tsproisl/CorpConv/archive/v0.1.1.tar.gz
Platform: UNKNOWN
Classifier: Development Status :: 4 - Beta
Classifier: Environment :: Console
Classifier: Intended Audience :: Developers
Classifier: Intended Audience :: Science/Research
Classifier: License :: OSI Approved :: GNU General Public License v3 or later (GPLv3+)
Classifier: Operating System :: OS Independent
Classifier: Programming Language :: Python :: 3
Classifier: Topic :: Text Processing :: Linguistic
